Workbook

Sheet Instrucciones
A1: Control de Gastos + Meta: Viaje a España
A3: CÓMO USARLO (5 minutos al día)
A4: 1. Hoja 'Presupuesto': revisa tu sueldo y el límite mensual de cada categoría (celdas amarillas).
A5: 2. Hoja 'Meta Viaje': ajusta el costo estimado del viaje y la fecha en que empiezas a ahorrar.
A6: 3. Hoja 'Registro': anota CADA gasto el mismo día (fecha, categoría, descripción, monto).
A7: 4. El día que recibes el sueldo, registra primero el ahorro del viaje (categoría 'Ahorro viaje') y transfiérelo a otra cuenta.
A8: 5. Hoja 'Resumen Mensual': elige el mes y mira cuánto te queda por categoría y cuánto puedes gastar por día.
A10: CÓDIGO DE COLORES
A11: Celdas amarillas con texto azul = datos que TÚ escribes o cambias.
A12: Texto negro = fórmulas (no las borres).
A13: En el Resumen: verde = vas bien, amarillo = usaste más del 80% del límite, rojo = te pasaste.
A15: REGLAS DE ORO
... A21: Nota: la fila 2 de 'Registro' es un ejemplo; reemplázala o bórrala con tus datos reales.

Sheet Presupuesto
A1: Presupuesto Mensual
A3: Sueldo mensual (USD) | B3: 1000
A5: Categoría | B5: Límite mensual (USD) | C5: % del sueldo | D5: Tipo | E5: Qué incluye
A6: Ahorro viaje | B6: ='Meta Viaje'!B18 | C6: =IF($B$3=0,0,B6/$B$3) | D6: Ahorro | E6: Se calcula solo desde 'Meta Viaje'. Transfiérelo el día de pago.
A7: Fondo de emergencia | B7: 50 | C7: =IF($B$3=0,0,B7/$B$3) | D7: Ahorro | E7: Para imprevistos reales, así no tocas el ahorro del viaje
A8: Vivienda | B8: 300 | C8: =IF($B$3=0,0,B8/$B$3) | D8: Necesidad | E8: Arriendo, aporte en casa
A9: Alimentación | B9: 170 | C9: =IF($B$3=0,0,B9/$B$3) | D9: Necesidad | E9: Supermercado, feria, almuerzos
A10: Transporte | B10: 70 | C10: =IF($B$3=0,0,B10/$B$3) | D10: Necesidad | E10: Pasajes, bencina, apps de transporte
A11: Servicios | B11: 70 | C11: =IF($B$3=0,0,B11/$B$3) | D11: Necesidad | E11: Luz, agua, gas, internet, celular
A12: Salud | B12: 30 | C12: =IF($B$3=0,0,B12/$B$3) | D12: Necesidad | E12: Farmacia, consultas
A13: Ocio y salidas | B13: 50 | C13: =IF($B$3=0,0,B13/$B$3) | D13: Gusto | E13: Comida fuera, delivery, salidas, streaming
A14: Ropa y cuidado personal | B14: 30 | C14: =IF($B$3=0,0,B14/$B$3) | D14: Gusto | E14: Ropa, peluquería, higiene
A15: Otros | B15: 30 | C15: =IF($B$3=0,0,B15/$B$3) | D15: Gusto | E15: Lo que no calce en otra categoría
A16: TOTAL ASIGNADO | B16: =SUM(B6:B15) | C16: =SUM(C6:C15)
A17: Sin asignar (sueldo - total) | B17: =B3-B16 | C17: =IF(B17<0,"¡Te pasaste! Baja algún límite",IF(B17>0,"Asígnalo (ideal: más ahorro)","Perfecto: cada dólar tiene destino"))
A19: Resumen por tipo
A20: Necesidad | B20: =SUMIFS($B$6:$B$15,$D$6:$D$15,A20) | C20: =IF($B$3=0,0,B20/$B$3)
A21: Gusto | B21: =SUMIFS($B$6:$B$15,$D$6:$D$15,A21) | C21: =IF($B$3=0,0,B21/$B$3)
A22: Ahorro | B22: =SUMIFS($B$6:$B$15,$D$6:$D$15,A22) | C22: =IF($B$3=0,0,B22/$B$3)
A23: Referencia: regla 50/30/20 → necesidades ≤ 50-60%, gustos ≤ 20-30%, ahorro ≥ 20%.

Sheet Registro
A1: Fecha | B1: Mes (auto) | C1: Categoría | D1: Descripción | E1: Monto (USD) | F1: Medio de pago
A2: 46298 | B2: =IF(A2="","",DATE(YEAR(A2),MONTH(A2),1)) | C2: Alimentación | D2: Supermercado (EJEMPLO, reemplázalo) | E2: 25.5 | F2: Débito
B3: =IF(A3="","",DATE(YEAR(A3),MONTH(A3),1))
B4: =IF(A4="","",DATE(YEAR(A4),MONTH(A4),1))
B5: =IF(A5="","",DATE(YEAR(A5),MONTH(A5),1))
B6: =IF(A6="","",DATE(YEAR(A6),MONTH(A6),1))
B7: =IF(A7="","",DATE(YEAR(A7),MONTH(A7),1))
B8: =IF(A8="","",DATE(YEAR(A8),MONTH(A8),1))
B9: =IF(A9="","",DATE(YEAR(A9),MONTH(A9),1))
B10: =IF(A10="","",DATE(YEAR(A10),MONTH(A10),1))
B11: =IF(A11="","",DATE(YEAR(A11),MONTH(A11),1))
B12: =IF(A12="","",DATE(YEAR(A12),MONTH(A12),1))
B13: =IF(A13="","",DATE(YEAR(A13),MONTH(A13),1))
B14: =IF(A14="","",DATE(YEAR(A14),MONTH(A14),1))
... B1501: =IF(A1501="","",DATE(YEAR(A1501),MONTH(A1501),1))

Sheet Resumen Mensual
A1: Resumen Mensual
A3: Mes a revisar (escribe el día 1 del mes) | B3: 46296
A4: Sueldo | B4: =Presupuesto!B3 | D4: Días que quedan del mes | E4: =IF(EOMONTH(B3,0)<TODAY(),0,EOMONTH(B3,0)-MAX(TODAY(),B3)+1)
A5: Total gastado + ahorrado | B5: =SUM(C9:C18) | D5: Disponible para gastos variables* | E5: =MAX(0,SUM(E12:E18))
A6: Te queda del sueldo | B6: =B4-B5 | D6: Puedes gastar por día | E6: =IF(E4=0,0,E5/E4)
D7: *Suma de lo disponible en Alimentación, Transporte, Servicios, Salud, Ocio, Ropa y Otros (no incluye ahorros ni vivienda).
A8: Categoría | B8: Límite | C8: Gastado | D8: % usado | E8: Disponible | F8: Estado
A9: =Presupuesto!A6 | B9: =Presupuesto!B6 | C9: =SUMIFS(Registro!$E:$E,Registro!$C:$C,A9,Registro!$B:$B,$B$3) | D9: =IF(B9=0,0,C9/B9) | E9: =B9-C9 | F9: =IF(D9>=1,"Cumplido","Falta ahorrar")
A10: =Presupuesto!A7 | B10: =Presupuesto!B7 | C10: =SUMIFS(Registro!$E:$E,Registro!$C:$C,A10,Registro!$B:$B,$B$3) | D10: =IF(B10=0,0,C10/B10) | E10: =B10-C10 | F10: =IF(D10>=1,"Cumplido","Falta ahorrar")
A11: =Presupuesto!A8 | B11: =Presupuesto!B8 | C11: =SUMIFS(Registro!$E:$E,Registro!$C:$C,A11,Registro!$B:$B,$B$3) | D11: =IF(B11=0,0,C11/B11) | E11: =B11-C11 | F11: =IF(D11>1,"Te pasaste",IF(D11>=0.8,"Cuidado","Bien"))
A12: =Presupuesto!A9 | B12: =Presupuesto!B9 | C12: =SUMIFS(Registro!$E:$E,Registro!$C:$C,A12,Registro!$B:$B,$B$3) | D12: =IF(B12=0,0,C12/B12) | E12: =B12-C12 | F12: =IF(D12>1,"Te pasaste",IF(D12>=0.8,"Cuidado","Bien"))
A13: =Presupuesto!A10 | B13: =Presupuesto!B10 | C13: =SUMIFS(Registro!$E:$E,Registro!$C:$C,A13,Registro!$B:$B,$B$3) | D13: =IF(B13=0,0,C13/B13) | E13: =B13-C13 | F13: =IF(D13>1,"Te pasaste",IF(D13>=0.8,"Cuidado","Bien"))
A14: =Presupuesto!A11 | B14: =Presupuesto!B11 | C14: =SUMIFS(Registro!$E:$E,Registro!$C:$C,A14,Registro!$B:$B,$B$3) | D14: =IF(B14=0,0,C14/B14) | E14: =B14-C14 | F14: =IF(D14>1,"Te pasaste",IF(D14>=0.8,"Cuidado","Bien"))
A15: =Presupuesto!A12 | B15: =Presupuesto!B12 | C15: =SUMIFS(Registro!$E:$E,Registro!$C:$C,A15,Registro!$B:$B,$B$3) | D15: =IF(B15=0,0,C15/B15) | E15: =B15-C15 | F15: =IF(D15>1,"Te pasaste",IF(D15>=0.8,"Cuidado","Bien"))
A16: =Presupuesto!A13 | B16: =Presupuesto!B13 | C16: =SUMIFS(Registro!$E:$E,Registro!$C:$C,A16,Registro!$B:$B,$B$3) | D16: =IF(B16=0,0,C16/B16) | E16: =B16-C16 | F16: =IF(D16>1,"Te pasaste",IF(D16>=0.8,"Cuidado","Bien"))
A17: =Presupuesto!A14 | B17: =Presupuesto!B14 | C17: =SUMIFS(Registro!$E:$E,Registro!$C:$C,A17,Registro!$B:$B,$B$3) | D17: =IF(B17=0,0,C17/B17) | E17: =B17-C17 | F17: =IF(D17>1,"Te pasaste",IF(D17>=0.8,"Cuidado","Bien"))
A18: =Presupuesto!A15 | B18: =Presupuesto!B15 | C18: =SUMIFS(Registro!$E:$E,Registro!$C:$C,A18,Registro!$B:$B,$B$3) | D18: =IF(B18=0,0,C18/B18) | E18: =B18-C18 | F18: =IF(D18>1,"Te pasaste",IF(D18>=0.8,"Cuidado","Bien"))
A19: TOTAL | B19: =SUM(B9:B18) | C19: =SUM(C9:C18) | D19: =IF(B19=0,0,C19/B19) | E19: =SUM(E9:E18)

Sheet Meta Viaje
A1: Meta: Viaje a España
A3: Parámetros
A4: Mes en que empiezas a ahorrar | B4: 46296
A5: Plazo (meses) | B5: 18
A6: Mes estimado del viaje | B6: =EDATE(B4,B5)
A8: Costo estimado del viaje (USD)
A9: Concepto | B9: Monto (USD) | C9: Supuesto
A10: Pasaje de avión ida y vuelta | B10: 1200 | C10: Estimado; compra con 3-5 meses de anticipación para mejor precio
A11: Alojamiento | B11: =15*45 | C11: 15 noches x $45 (hostal / Airbnb económico)
A12: Comida | B12: =15*35 | C12: 15 días x $35
A13: Transporte dentro de España | B13: 250 | C13: Metro, buses, un tren entre ciudades
A14: Actividades / entradas | B14: 200 | C14: Museos, tours
A15: Seguro de viaje (Schengen) | B15: 60 | C15: Obligatorio para entrar a Europa
A16: Imprevistos (10%) | B16: =SUM(B10:B15)*0.1 | C16: Colchón de seguridad
A17: TOTAL META | B17: =SUM(B10:B16)
A18: Ahorro mensual necesario | B18: =B17/B5
A20: Ahorrado hasta ahora | B20: =SUMIFS(Registro!E:E,Registro!C:C,"Ahorro viaje")
A21: Te falta | B21: =MAX(0,B17-B20)
A22: Progreso | B22: =IF(B17=0,0,B20/B17)
A24: Mes | B24: Ahorro planificado | C24: Ahorro real | D24: Acumulado planificado | E24: Acumulado real | F24: Diferencia | G24: Estado
A25: =EDATE($B$4,0) | B25: =$B$18 | C25: =SUMIFS(Registro!$E:$E,Registro!$C:$C,"Ahorro viaje",Registro!$B:$B,A25) | D25: =SUM($B$25:B25) | E25: =SUM($C$25:C25) | F25: =E25-D25 | G25: =IF(A25>TODAY(),"Pendiente",IF(F25>=0,"Al día","Atrasado"))
A26: =EDATE($B$4,1) | B26: =$B$18 | C26: =SUMIFS(Registro!$E:$E,Registro!$C:$C,"Ahorro viaje",Registro!$B:$B,A26) | D26: =SUM($B$25:B26) | E26: =SUM($C$25:C26) | F26: =E26-D26 | G26: =IF(A26>TODAY(),"Pendiente",IF(F26>=0,"Al día","Atrasado"))
A27: =EDATE($B$4,2) | B27: =$B$18 | C27: =SUMIFS(Registro!$E:$E,Registro!$C:$C,"Ahorro viaje",Registro!$B:$B,A27) | D27: =SUM($B$25:B27) | E27: =SUM($C$25:C27) | F27: =E27-D27 | G27: =IF(A27>TODAY(),"Pendiente",IF(F27>=0,"Al día","Atrasado"))
A28: =EDATE($B$4,3) | B28: =$B$18 | C28: =SUMIFS(Registro!$E:$E,Registro!$C:$C,"Ahorro viaje",Registro!$B:$B,A28) | D28: =SUM($B$25:B28) | E28: =SUM($C$25:C28) | F28: =E28-D28 | G28: =IF(A28>TODAY(),"Pendiente",IF(F28>=0,"Al día","Atrasado"))
A29: =EDATE($B$4,4) | B29: =$B$18 | C29: =SUMIFS(Registro!$E:$E,Registro!$C:$C,"Ahorro viaje",Registro!$B:$B,A29) | D29: =SUM($B$25:B29) | E29: =SUM($C$25:C29) | F29: =E29-D29 | G29: =IF(A29>TODAY(),"Pendiente",IF(F29>=0,"Al día","Atrasado"))
A30: =EDATE($B$4,5) | B30: =$B$18 | C30: =SUMIFS(Registro!$E:$E,Registro!$C:$C,"Ahorro viaje",Registro!$B:$B,A30) | D30: =SUM($B$25:B30) | E30: =SUM($C$25:C30) | F30: =E30-D30 | G30: =IF(A30>TODAY(),"Pendiente",IF(F30>=0,"Al día","Atrasado"))
A31: =EDATE($B$4,6) | B31: =$B$18 | C31: =SUMIFS(Registro!$E:$E,Registro!$C:$C,"Ahorro viaje",Registro!$B:$B,A31) | D31: =SUM($B$25:B31) | E31: =SUM($C$25:C31) | F31: =E31-D31 | G31: =IF(A31>TODAY(),"Pendiente",IF(F31>=0,"Al día","Atrasado"))
A32: =EDATE($B$4,7) | B32: =$B$18 | C32: =SUMIFS(Registro!$E:$E,Registro!$C:$C,"Ahorro viaje",Registro!$B:$B,A32) | D32: =SUM($B$25:B32) | E32: =SUM($C$25:C32) | F32: =E32-D32 | G32: =IF(A32>TODAY(),"Pendiente",IF(F32>=0,"Al día","Atrasado"))
A33: =EDATE($B$4,8) | B33: =$B$18 | C33: =SUMIFS(Registro!$E:$E,Registro!$C:$C,"Ahorro viaje",Registro!$B:$B,A33) | D33: =SUM($B$25:B33) | E33: =SUM($C$25:C33) | F33: =E33-D33 | G33: =IF(A33>TODAY(),"Pendiente",IF(F33>=0,"Al día","Atrasado"))
A34: =EDATE($B$4,9) | B34: =$B$18 | C34: =SUMIFS(Registro!$E:$E,Registro!$C:$C,"Ahorro viaje",Registro!$B:$B,A34) | D34: =SUM($B$25:B34) | E34: =SUM($C$25:C34) | F34: =E34-D34 | G34: =IF(A34>TODAY(),"Pendiente",IF(F34>=0,"Al día","Atrasado"))
A35: =EDATE($B$4,10) | B35: =$B$18 | C35: =SUMIFS(Registro!$E:$E,Registro!$C:$C,"Ahorro viaje",Registro!$B:$B,A35) | D35: =SUM($B$25:B35) | E35: =SUM($C$25:C35) | F35: =E35-D35 | G35: =IF(A35>TODAY(),"Pendiente",IF(F35>=0,"Al día","Atrasado"))
A36: =EDATE($B$4,11) | B36: =$B$18 | C36: =SUMIFS(Registro!$E:$E,Registro!$C:$C,"Ahorro viaje",Registro!$B:$B,A36) | D36: =SUM($B$25:B36) | E36: =SUM($C$25:C36) | F36: =E36-D36 | G36: =IF(A36>TODAY(),"Pendiente",IF(F36>=0,"Al día","Atrasado"))
A37: =EDATE($B$4,12) | B37: =$B$18 | C37: =SUMIFS(Registro!$E:$E,Registro!$C:$C,"Ahorro viaje",Registro!$B:$B,A37) | D37: =SUM($B$25:B37) | E37: =SUM($C$25:C37) | F37: =E37-D37 | G37: =IF(A37>TODAY(),"Pendiente",IF(F37>=0,"Al día","Atrasado"))
A38: =EDATE($B$4,13) | B38: =$B$18 | C38: =SUMIFS(Registro!$E:$E,Registro!$C:$C,"Ahorro viaje",Registro!$B:$B,A38) | D38: =SUM($B$25:B38) | E38: =SUM($C$25:C38) | F38: =E38-D38 | G38: =IF(A38>TODAY(),"Pendiente",IF(F38>=0,"Al día","Atrasado"))
A39: =EDATE($B$4,14) | B39: =$B$18 | C39: =SUMIFS(Registro!$E:$E,Registro!$C:$C,"Ahorro viaje",Registro!$B:$B,A39) | D39: =SUM($B$25:B39) | E39: =SUM($C$25:C39) | F39: =E39-D39 | G39: =IF(A39>TODAY(),"Pendiente",IF(F39>=0,"Al día","Atrasado"))
A40: =EDATE($B$4,15) | B40: =$B$18 | C40: =SUMIFS(Registro!$E:$E,Registro!$C:$C,"Ahorro viaje",Registro!$B:$B,A40) | D40: =SUM($B$25:B40) | E40: =SUM($C$25:C40) | F40: =E40-D40 | G40: =IF(A40>TODAY(),"Pendiente",IF(F40>=0,"Al día","Atrasado"))
A41: =EDATE($B$4,16) | B41: =$B$18 | C41: =SUMIFS(Registro!$E:$E,Registro!$C:$C,"Ahorro viaje",Registro!$B:$B,A41) | D41: =SUM($B$25:B41) | E41: =SUM($C$25:C41) | F41: =E41-D41 | G41: =IF(A41>TODAY(),"Pendiente",IF(F41>=0,"Al día","Atrasado"))
A42: =EDATE($B$4,17) | B42: =$B$18 | C42: =SUMIFS(Registro!$E:$E,Registro!$C:$C,"Ahorro viaje",Registro!$B:$B,A42) | D42: =SUM($B$25:B42) | E42: =SUM($C$25:C42) | F42: =E42-D42 | G42: =IF(A42>TODAY(),"Pendiente",IF(F42>=0,"Al día","Atrasado"))
